hoots/__init__.py
hoots/client.py
hoot_api-0.0.35.dist-info/LICENSE.txt
hoot_api-0.0.35.dist-info/METADATA
hoot_api-0.0.35.dist-info/WHEEL
hoot_api-0.0.35.dist-info/top_level.txt
hoot_api-0.0.35.dist-info/RECORD
